if_.py
if_optional-0.0.3.dist-info/LICENSE.txt
if_optional-0.0.3.dist-info/METADATA
if_optional-0.0.3.dist-info/WHEEL
if_optional-0.0.3.dist-info/top_level.txt
if_optional-0.0.3.dist-info/RECORD
