Metadata-Version: 2.1
Name: if_optional
Version: 0.0.3
Summary: Optional chaining for Python
Home-page: http://github.com/nicwolff/if_
Author: Nic Wolff
Author-email: nic@angel.net
License: MIT
License-File: LICENSE.txt
